poetry_demo_1199/__init__.py
poetry_demo_1199/demo.py
poetry_demo_1199-0.1.0.dist-info/WHEEL
poetry_demo_1199-0.1.0.dist-info/METADATA
poetry_demo_1199-0.1.0.dist-info/RECORD
