Metadata-Version: 2.1
Name: poetry-demo-1199
Version: 0.1.0
Summary: Demo of poetry for akashkj.com
Author: Akash
Requires-Python: >=3.7,<4.0
Classifier: Programming Language :: Python :: 3
Classifier: Programming Language :: Python :: 3.10
Classifier: Programming Language :: Python :: 3.7
Classifier: Programming Language :: Python :: 3.8
Classifier: Programming Language :: Python :: 3.9
Requires-Dist: mypy (>=0.910,<0.911)
Requires-Dist: requests (>=2.26.0,<3.0.0)
